goldfish_cli/__init__.py
goldfish_cli/capture.py
goldfish_cli/config.py
goldfish_cli/dashboard.py
goldfish_cli/main.py
goldfish_cli/repl.py
goldfish_cli/suggestions.py
goldfish_cli-0.1.4.dist-info/METADATA
goldfish_cli-0.1.4.dist-info/WHEEL
goldfish_cli-0.1.4.dist-info/entry_points.txt
goldfish_cli-0.1.4.dist-info/licenses/LICENSE
goldfish_cli-0.1.4.dist-info/RECORD
