Metadata-Version: 2.4
Name: goldfish-cli
Version: 0.1.4
Summary: AI-First Personal Knowledge Management CLI
Project-URL: Homepage, https://github.com/linxichen/goldfish
Project-URL: Repository, https://github.com/linxichen/goldfish
Project-URL: Documentation, https://github.com/linxichen/goldfish/tree/main/goldfish-cli
Project-URL: Bug Reports, https://github.com/linxichen/goldfish/issues
Author: Goldfish Team
License: MIT License
License-File: LICENSE
Keywords: ai,cli,entities,knowledge,management,notes
Classifier: Development Status :: 3 - Alpha
Classifier: Environment :: Console
Classifier: Intended Audience :: End Users/Desktop
Classifier: License :: OSI Approved :: MIT License
Classifier: Operating System :: OS Independent
Classifier: Programming Language :: Python :: 3
Classifier: Programming Language :: Python :: 3.11
Classifier: Programming Language :: Python :: 3.12
Classifier: Topic :: Office/Business :: Scheduling
Classifier: Topic :: Scientific/Engineering :: Artificial Intelligence
Classifier: Topic :: Text Processing
Requires-Python: >=3.11
Requires-Dist: click>=8.2.1
Requires-Dist: goldfish-backend>=0.1.0
Requires-Dist: prompt-toolkit>=3.0.51
Requires-Dist: rich>=14.0.0
Provides-Extra: dev
Requires-Dist: black>=24.0.0; extra == 'dev'
Requires-Dist: faker>=37.4.0; extra == 'dev'
Requires-Dist: mypy>=1.8.0; extra == 'dev'
Requires-Dist: pytest-asyncio>=1.0.0; extra == 'dev'
Requires-Dist: pytest-cov>=6.2.1; extra == 'dev'
Requires-Dist: pytest>=8.4.1; extra == 'dev'
Requires-Dist: ruff>=0.6.0; extra == 'dev'
